cdk_home_assistant_skill/__init__.py
cdk_home_assistant_skill/py.typed
cdk_home_assistant_skill/_jsii/__init__.py
cdk_home_assistant_skill/_jsii/cdk-home-assistant-skill@0.0.1.jsii.tgz
cdk_home_assistant_skill-0.0.1.dist-info/LICENSE
cdk_home_assistant_skill-0.0.1.dist-info/METADATA
cdk_home_assistant_skill-0.0.1.dist-info/WHEEL
cdk_home_assistant_skill-0.0.1.dist-info/top_level.txt
cdk_home_assistant_skill-0.0.1.dist-info/RECORD
