Metadata-Version: 2.1
Name: cdk-home-assistant-skill
Version: 0.0.1
Summary: cdk-home-assistant-skill
Home-page: https://github.com/t0bst4r/cdk-home-assistant-skill.git
Author: t0bst4r<82281152+t0bst4r@users.noreply.github.com>
License: Apache-2.0
Project-URL: Source, https://github.com/t0bst4r/cdk-home-assistant-skill.git
Classifier: Intended Audience :: Developers
Classifier: Operating System :: OS Independent
Classifier: Programming Language :: JavaScript
Classifier: Programming Language :: Python :: 3 :: Only
Classifier: Programming Language :: Python :: 3.8
Classifier: Programming Language :: Python :: 3.9
Classifier: Programming Language :: Python :: 3.10
Classifier: Programming Language :: Python :: 3.11
Classifier: Typing :: Typed
Classifier: Development Status :: 5 - Production/Stable
Classifier: License :: OSI Approved
Requires-Python: ~=3.8
License-File: LICENSE
Requires-Dist: aws-cdk-lib <3.0.0,>=2.88.0
Requires-Dist: cdk-skill-management <2.0.0,>=1.0.28
Requires-Dist: constructs <11.0.0,>=10.0.5
Requires-Dist: jsii <2.0.0,>=1.92.0
Requires-Dist: publication >=0.0.3
Requires-Dist: typeguard ~=2.13.3
